greenviz
zeptosoft
