Metadata-Version: 1.0
Name: zeptosoft
Version: 0.3
Summary: creating our first package
Home-page: UNKNOWN
Author: D.Achuth
Author-email: achuthaiml@gmail.com
License: UNKNOWN
Platform: UNKNOWN
